tf2_sku/__init__.py
tf2_sku/sku.py
tf2_sku/utils.py
tf2_sku-2.0.1.dist-info/LICENSE
tf2_sku-2.0.1.dist-info/METADATA
tf2_sku-2.0.1.dist-info/WHEEL
tf2_sku-2.0.1.dist-info/top_level.txt
tf2_sku-2.0.1.dist-info/RECORD
