Metadata-Version: 2.1
Name: tf2-sku
Version: 2.0.1
Summary: Parse TF2 items to SKU format
Author-email: offish <overutilization@gmail.com>
Project-URL: Homepage, https://github.com/offish/tf2-sku
Project-URL: Bug Tracker, https://github.com/offish/tf2-sku/issues
Keywords: tf2,sku
Classifier: Programming Language :: Python :: 3
Classifier: License :: OSI Approved :: MIT License
Classifier: Operating System :: OS Independent
Requires-Python: >=3.7
License-File: LICENSE
